greek_stemmer
greparl
mock
test
