Metadata-Version: 2.1
Name: GreParl
Version: 0.3
Summary: Grep the Greek Parliament
Home-page: https://github.com/GeorgeVasiliadis/GreParl
Author: George Vasiliadis
Author-email: geor.vasiliadis@gmail.com
License: UNKNOWN
Platform: UNKNOWN
Classifier: Topic :: Internet :: WWW/HTTP :: WSGI :: Application
Classifier: Topic :: Internet :: WWW/HTTP :: Indexing/Search
Classifier: Topic :: Software Development :: User Interfaces
Classifier: Operating System :: OS Independent
Classifier: Framework :: Flask
Classifier: Programming Language :: Python :: 3
Classifier: License :: OSI Approved :: MIT License
Requires-Python: >=3.6
License-File: LICENSE
